README.md
setup.py
dptools/__init__.py
dptools/conftest.py
dptools/data_cleaning.py
dptools/data_processing.py
dptools/feature_engineering.py
dptools/import_and_versioning.py
dptools.egg-info/PKG-INFO
dptools.egg-info/SOURCES.txt
dptools.egg-info/dependency_links.txt
dptools.egg-info/not-zip-safe
dptools.egg-info/requires.txt
dptools.egg-info/top_level.txt