Metadata-Version: 2.1
Name: dptools
Version: 0.3.11
Summary: Data Preprocessing Tools
Home-page: https://github.com/kozodoi/dptools
Author: Nikita Kozodoi
Author-email: n.kozodoi@icloud.com
License: MIT
Platform: UNKNOWN
